pygitpub/__init__.py
pygitpub/configs.py
pygitpub/main.py
pygitpub/static.py
pygitpub/utils/__init__.py
pygitpub/utils/importlib.py
pygitpub/utils/misc.py
pygitpub-0.0.58.dist-info/METADATA
pygitpub-0.0.58.dist-info/WHEEL
pygitpub-0.0.58.dist-info/entry_points.txt
pygitpub-0.0.58.dist-info/licenses/LICENSE
pygitpub-0.0.58.dist-info/RECORD
