Metadata-Version: 2.4
Name: pygitpub
Version: 0.0.58
Summary: Pygitpub will help you work with github
Project-URL: Homepage, https://github.com/veltzer/pygitpub
Project-URL: Bug Tracker, https://github.com/veltzer/pygitpub/issues
Project-URL: Documentation, https://veltzer.github.io/pygitpub
Project-URL: Download, https://pypi.org/project/pygitpub/
Project-URL: Repository, https://github.com/veltzer/pygitpub
Author-email: Mark Veltzer <mark.veltzer@gmail.com>
Maintainer-email: Mark Veltzer <mark.veltzer@gmail.com>
License-Expression: MIT
License-File: LICENSE
Keywords: github,pygithub
Classifier: Development Status :: 4 - Beta
Classifier: Environment :: Console
Classifier: License :: OSI Approved :: MIT License
Classifier: Operating System :: OS Independent
Classifier: Programming Language :: Python
Classifier: Programming Language :: Python :: 3
Classifier: Programming Language :: Python :: 3 :: Only
Classifier: Programming Language :: Python :: 3.12
Classifier: Topic :: Utilities
Requires-Python: >=3.12
Requires-Dist: pyapikey
Requires-Dist: pygithub
Requires-Dist: pylogconf
Requires-Dist: pytconf
Requires-Dist: pyyaml
